pycuga/__init__.py
pycuga/info.py
pycuga/pycuga.py
pycuga/test.py
pycuga/algos/__init__.py
pycuga/algos/tools.py
issacto-0.0.2.dist-info/LICENSE
issacto-0.0.2.dist-info/METADATA
issacto-0.0.2.dist-info/WHEEL
issacto-0.0.2.dist-info/top_level.txt
issacto-0.0.2.dist-info/RECORD
